[{"name":"TEst","date":"2024-05-06","startTime":"12:01","endTime":"20:20","interrupts":"","comments":""},{"name":"Aha","date":"2024-05-06","startTime":"12:01","endTime":"20:21","interrupts":"","comments":""},{"name":"Programavimas","date":"2024-05-06","startTime":"10:00","endTime":"12:30","interrupts":"","comments":""},{"name":"14","date":"2024-02-24","startTime":"12:30","endTime":"13:30","interrupts":"","comments":""},{"name":"test134","date":"2024-02-23","startTime":"23:30","endTime":"23:35","interrupts":"","comments":""},{"name":"23","date":"2024-02-21","startTime":"12:45","endTime":"12:46","interrupts":"","comments":""}]